{
  "actives": [
    {
      "id": 1621354863022,
      "createdBy": "260908777446965248",
      "archived": false,
      "template": "echecs",
      "date": "2021-05-21T18:30:00.000Z",
      "teams": 0,
      "exteriorMembers": true,
      "roleReactionMessage": "844248387263004722",
      "participants": [],
      "category": {
        "name": "『♟️』 Échecs - 21/05",
        "id": "844248376883150849"
      },
      "channels": [
        {
          "name": "📃｜règlement",
          "type": "text",
          "permissionsAuth": [
            "VIEW_CHANNEL"
          ],
          "permissionsForbid": [
            "SEND_MESSAGES"
          ],
          "defaultMessage": "",
          "id": "844248379076771910"
        },
        {
          "name": "🏆｜scores",
          "type": "text",
          "permissionsAuth": [
            "VIEW_CHANNEL"
          ],
          "permissionsForbid": [
            "SEND_MESSAGES"
          ],
          "defaultMessage": "",
          "id": "844248379406942239"
        },
        {
          "name": "🌍｜général",
          "type": "text",
          "permissionsAuth": [
            "VIEW_CHANNEL"
          ],
          "permissionsForbid": [],
          "defaultMessage": "",
          "id": "844248380570075146"
        },
        {
          "name": "▬▬▬▬▬▬▬▬▬",
          "type": "text",
          "permissionsAuth": [],
          "permissionsForbid": [],
          "defaultMessage": "",
          "id": "844248381286776862"
        },
        {
          "name": "⚙｜orga",
          "type": "text",
          "permissionsAuth": [],
          "permissionsForbid": [],
          "defaultMessage": "",
          "id": "844248385338998844"
        },
        {
          "name": "▬▬▬▬▬▬▬▬▬",
          "type": "text",
          "permissionsAuth": [
            "VIEW_CHANNEL"
          ],
          "permissionsForbid": [
            "SEND_MESSAGES"
          ],
          "defaultMessage": "",
          "id": "844248386461892608"
        },
        {
          "name": "♟ ➤ Échecs",
          "type": "voice",
          "permissionsAuth": ["VIEW_CHANNEL"],
          "permissionsForbid": [],
          "defaultMessage": "",
          "id": "844501016002822154"
      }
      ],
      "roles": [
        {
          "name": "▬▬▬▬▬",
          "color": null,
          "separatorRole": true,
          "id": "844248374785998898"
        },
        {
          "name": "『♟️』 Échecs - 21/05",
          "color": null,
          "defaultRole": true,
          "id": "844248375556702218"
        },
        {
          "name": "🦺 Échecs Orga - 21/05",
          "color": "ff0000",
          "orgaRole": true,
          "id": "844248376409325638"
        }
      ]
    }
  ],
  "archived": []
}